topojson/__init__.py
topojson/ops.py
topojson/utils.py
topojson/core/__init__.py
topojson/core/cut.py
topojson/core/dedup.py
topojson/core/extract.py
topojson/core/hashmap.py
topojson/core/join.py
topojson/core/topology.py
topojson-1.6.dist-info/LICENSE
topojson-1.6.dist-info/WHEEL
topojson-1.6.dist-info/METADATA
topojson-1.6.dist-info/RECORD
