Metadata-Version: 2.1
Name: topojson
Version: 1.6
Summary: topojson - a powerful library to encode geographic data as topology in Python!🌍
Keywords: topojson,python,github,topology,geojson
Author-email: Mattijn van Hoek <mattijn@gmail.com>
Classifier: License :: OSI Approved :: BSD License
Requires-Dist: numpy
Requires-Dist: shapely
Requires-Dist: packaging
Requires-Dist: geopandas ; extra == "dev"
Requires-Dist: geojson ; extra == "dev"
Requires-Dist: simplification ; extra == "dev"
Requires-Dist: pyshp ; extra == "dev"
Requires-Dist: altair ; extra == "dev"
Requires-Dist: ipywidgets ; extra == "dev"
Project-URL: Documentation, https://mattijn.github.io/topojson
Project-URL: Releases, https://github.com/mattijn/topojson/releases
Project-URL: Source, https://github.com/mattijn/topojson
Provides-Extra: dev
